madgrad/__init__.py
madgrad/madgrad.py
tf_madgrad-1.0.2.dist-info/LICENSE
tf_madgrad-1.0.2.dist-info/METADATA
tf_madgrad-1.0.2.dist-info/WHEEL
tf_madgrad-1.0.2.dist-info/top_level.txt
tf_madgrad-1.0.2.dist-info/RECORD
