Metadata-Version: 2.1
Name: tf-madgrad
Version: 1.0.2
Summary: A tf.keras implementation of the MADGRAD optimization algorithm
Home-page: https://github.com/DarshanDeshpande/tf-madgrad
Author: Darshan Deshpande
Author-email: darshan1504@gmail.com
License: MIT
Classifier: Development Status :: 5 - Production/Stable
Classifier: License :: OSI Approved :: MIT License
Classifier: Programming Language :: Python :: 3.6
Classifier: Programming Language :: Python :: 3.7
Classifier: Programming Language :: Python :: 3.8
Requires-Python: >=3.6.0
License-File: LICENSE
Requires-Dist: tensorflow (>=2.0)
